WattTime/WattTime.py
WattTime/__init__.py
watttime_api_wrapper-1.0.2.dist-info/LICENSE
watttime_api_wrapper-1.0.2.dist-info/METADATA
watttime_api_wrapper-1.0.2.dist-info/WHEEL
watttime_api_wrapper-1.0.2.dist-info/top_level.txt
watttime_api_wrapper-1.0.2.dist-info/RECORD
