Metadata-Version: 2.1
Name: watttime-api-wrapper
Version: 1.0.2
Summary: Python API wrapper for the WattTime API
Home-page: https://github.com/aarongzmn/watttime-api-wrapper
Author: Aaron Guzman
Author-email: aarongzmn@gmail.com
Project-URL: Bug Tracker, https://github.com/aarongzmn/watttime-api-wrapper/issues
Classifier: Programming Language :: Python :: 3
Classifier: License :: OSI Approved :: MIT License
Classifier: Operating System :: OS Independent
Requires-Python: >=3.7
License-File: LICENSE
